lusos/__init__.py
lusos/area_statistics.py
lusos/constants.py
lusos/coverage.py
lusos/emissions.py
lusos/lasso.py
lusos/utils.py
lusos/data/__init__.py
lusos/data/emission_factors.py
lusos/data/registry.txt
lusos/geometry/__init__.py
lusos/geometry/ops.py
lusos/preprocessing/__init__.py
lusos/preprocessing/bgt.py
lusos/preprocessing/soilmap.py
lusos/preprocessing/somers.py
lusos/readers/__init__.py
lusos/readers/geopackage.py
lusos/readers/read_soilmap.py
lusos/validation/__init__.py
lusos/validation/exceptions.py
lusos/validation/validate.py
lusos/validation/validators.py
lusos-0.2.4.dist-info/METADATA
lusos-0.2.4.dist-info/WHEEL
lusos-0.2.4.dist-info/licenses/LICENSE
lusos-0.2.4.dist-info/RECORD
