Metadata-Version: 2.4
Name: lusos
Version: 0.2.4
Summary: Spatial calculation of GHG emissions from SOMERS modelling results
Project-URL: Homepage, https://github.com/Deltares-research/lulucf-somers
Project-URL: Repository, https://github.com/Deltares-research/lulucf-somers
Project-URL: Issues, https://github.com/Deltares-research/lulucf-somers/issues
Author-email: smknaake <bas.knaake@deltares.nl>
License: MIT License
License-File: LICENSE
Keywords: BRO Bodemkaart,Basis Registratie Grootschalige Topografie,Deltares,Greenhouse gas emission,LULUCF,Lasso,SOMERS
Classifier: Development Status :: 2 - Pre-Alpha
Classifier: Intended Audience :: Science/Research
Classifier: License :: OSI Approved :: MIT License
Classifier: Operating System :: OS Independent
Classifier: Programming Language :: Python
Classifier: Programming Language :: Python :: 3.12
Classifier: Topic :: Scientific/Engineering
Requires-Python: >=3.12
Requires-Dist: dask
Requires-Dist: fiona
Requires-Dist: geopandas
Requires-Dist: h5netcdf
Requires-Dist: mapbox-earcut
Requires-Dist: netcdf4
Requires-Dist: numba
Requires-Dist: numba-celltree
Requires-Dist: numpy
Requires-Dist: pandas
Requires-Dist: pooch
Requires-Dist: pyarrow
Requires-Dist: rioxarray
Requires-Dist: xarray
Requires-Dist: xugrid
